findapp/__init__.py
findapp/base.py
findapp/macos.py
findapp/posix.py
findapp/windows.py
findapp-0.0.1.dist-info/LICENSE
findapp-0.0.1.dist-info/WHEEL
findapp-0.0.1.dist-info/METADATA
findapp-0.0.1.dist-info/RECORD
